{
  "power-strike": {
    "id": "power-strike",
    "name": "Power Strike",
    "description": "Increases melee attack damage.",
    "type": "passive",
    "cost": 1,
    "prerequisites": [],
    "effects": [
      { "type": "increase_attack", "potency": 1, "requiresTarget": false }
    ]
  },
  "toughness": {
    "id": "toughness",
    "name": "Toughness",
    "description": "Increases maximum HP.",
    "type": "passive",
    "cost": 1,
    "prerequisites": [],
    "effects": [
      { "type": "increase_max_hp", "potency": 5, "requiresTarget": false }
    ]
  },
  "cleave": {
    "id": "cleave",
    "name": "Cleave",
    "description": "Attack multiple adjacent enemies.",
    "type": "active",
    "combatActionId": "cleave",
    "cost": 2,
    "apCost": 2,
    "prerequisites": ["power-strike"]
  },
  "berserk": {
    "id": "berserk",
    "name": "Berserk",
    "description": "Enter a berserker rage, increasing attack but lowering defense.",
    "type": "active",
    "combatActionId": "berserk",
    "cost": 3,
    "apCost": 3,
    "prerequisites": ["power-strike", "toughness"]
  },
  "fireball": {
    "id": "fireball",
    "name": "Fireball",
    "description": "Hurls a ball of fire at a target.",
    "type": "active",
    "cost": 2,
    "apCost": 2,
    "prerequisites": [],
    "effects": [
      {
        "type": "fireball",
        "potency": 10,
        "radius": 3,
        "requiresTarget": true
      }
    ]
  }
}
